Workbook

Sheet all_edges
A1: FCM | B1: from | C1: to | D1: weight
A2: 2 | B2: rainfall | C2: food security | D2: 3
A3: 2 | B3: rainfall | C3: travel to distant water sources | D3: -2
A4: 2 | B4: rainfall | C4: surface runoff | D4: 3
A5: 2 | B5: rainfall | C5: food aid | D5: -1
A6: 2 | B6: rainfall | C6: vector populations | D6: 3
A7: 2 | B7: vector populations | C7: livestock disease | D7: -2
A8: 2 | B8: livestock disease | C8: livestock body condition | D8: -2
A9: 2 | B9: livestock disease | C9: milk production | D9: -2
A10: 2 | B10: livestock disease | C10: meat availability | D10: -2
A11: 2 | B11: milk production | C11: income | D11: 2
A12: 2 | B12: meat availability | C12: income | D12: 2
A13: 2 | B13: income | C13: financial security | D13: 3
... A2903: 36 | B2903: improved breeds | C2903: drought resilience | D2903: 2

Sheet edits
A1: # | B1: FCM | C1: Concept or edge affected | D1: Change | E1: Justification
A2: 1 | B2: 2 | C2: biting flies population | D2: vector populations | E2: harmonisation with other FCMS
A3: 2 | B3: 2 | C3: lack of use of water points | D3: use of water points | E3: reversed logic for simplicity, and reversed sign of connected edges
A4: 3 | B4: 2 | C4: stagnant | D4: stagnant water | E4: clarification
A5: 4 | B5: 2 | C5: permanance of homestead/sedentarisation | D5: sedentarisation | E5: simplification
A6: 5 | B6: 2 | C6: more possessions | D6: household possessions | E6: removed comparative degree marker as concepts must be variable and added 'household' for clarification
A7: 6 | B7: 2 | C7: livestock condition | D7: livestock body condition | E7: clarification
A8: 7 | B8: 2 | C8: livestock colour | D8: removed | E8: equivalent to livestock body condition
A9: 8 | B9: 2 | C9: accumulation of dirtiness (rubbish & faeces) | D9: environmental faecal contamination | E9: harmonisation with other FCMS
A10: 9 | B10: 2 | C10: livelihood | D10: income | E10: livelihood cannot increase or decrease
A11: 10 | B11: 2 | C11: livestock disease -> livestock body condition | D11: added weight -2 | E11: sign recorded but no weight, assumed central value
A12: 11 | B12: 2 | C12: accumulation of livestock faeces | D12: removed | E12: equivalent to 'environmental faecal contamination'
A13: 12 | B13: 2 | C13: mobility of homestead | D13: mobility | E13: harmonisation with other FCMS
... A1126: 1125 | B1126: 36 | C1126: livestock drug purchase | D1126: veterinary services | E1126: harmonisation with other FCMs

Sheet edits_formatted
A1: # | B1: FCM | C1: Element Type | D1: Change | F1: Old Concept/Edge Source | G1: Old Target | H1: New Concept/Edge Source | I1: New Target | J1: New Weight | K1: Justification
A2: 1 | B2: =edits!B2 -> 2 | C2: =IF(ISNUMBER(SEARCH("->",edits!C2)), "Edge", "Node") -> Node | D2: =edits!D2 -> vector populations | F2: =IFERROR(TRIM(LEFT(edits!C2, FIND("->", edits!C2) - 1)),edits!C2) -> biting flies population | G2: =IFERROR(TRIM(MID(edits!C2, FIND("->",edits!C2) + 2, LEN(edits!C2))),"") | H2: =IF(ISNUMBER(SEARCH("removed", edits!D2)), "", IF(ISNUMBER(SEARCH("->", edits!D2)), TRIM(LEFT(edits!D2, FIND("->", edits!D2)-1)), IF(ISNUMBER(SEARCH("->", edits!C2)), TRIM(LEFT(edits!C2, FIND("->", edits!C2)-1)), edits!D2))) -> vector populations | I2: =IF(ISNUMBER(SEARCH("->", edits!D2)), TRIM(MID(edits!D2, FIND("->", edits!D2) + 2, LEN(edits!D2))), IF(ISNUMBER(SEARCH("->", edits!C2)), TRIM(MID(edits!C2, FIND("->", edits!C2) + 2, LEN(edits!C2))), "")) | J2: {=IF(OR(H2="", I2=""), "", INDEX(all_edges!D:D, MATCH(1, (all_edges!A:A=B2) * (all_edges!B:B=H2) * (all_edges!C:C=I2), 0) ) )} | K2: =edits!E2 -> harmonisation with other FCMS
A3: 2 | B3: =edits!B3 -> 2 | C3: =IF(ISNUMBER(SEARCH("->",edits!C3)), "Edge", "Node") -> Node | D3: =edits!D3 -> use of water points | F3: =IFERROR(TRIM(LEFT(edits!C3, FIND("->", edits!C3) - 1)),edits!C3) -> lack of use of water points | G3: =IFERROR(TRIM(MID(edits!C3, FIND("->",edits!C3) + 2, LEN(edits!C3))),"") | H3: =IF(ISNUMBER(SEARCH("removed", edits!D3)), "", IF(ISNUMBER(SEARCH("->", edits!D3)), TRIM(LEFT(edits!D3, FIND("->", edits!D3)-1)), IF(ISNUMBER(SEARCH("->", edits!C3)), TRIM(LEFT(edits!C3, FIND("->", edits!C3)-1)), edits!D3))) -> use of water points | I3: =IF(ISNUMBER(SEARCH("->", edits!D3)), TRIM(MID(edits!D3, FIND("->", edits!D3) + 2, LEN(edits!D3))), IF(ISNUMBER(SEARCH("->", edits!C3)), TRIM(MID(edits!C3, FIND("->", edits!C3) + 2, LEN(edits!C3))), "")) | J3: {=IF(OR(H3="", I3=""), "", INDEX(all_edges!D:D, MATCH(1, (all_edges!A:A=B3) * (all_edges!B:B=H3) * (all_edges!C:C=I3), 0) ) )} | K3: =edits!E3 -> reversed logic for simplicity, and reversed sign of connected edges
A4: 3 | B4: =edits!B4 -> 2 | C4: =IF(ISNUMBER(SEARCH("->",edits!C4)), "Edge", "Node") -> Node | D4: =edits!D4 -> stagnant water | F4: =IFERROR(TRIM(LEFT(edits!C4, FIND("->", edits!C4) - 1)),edits!C4) -> stagnant | G4: =IFERROR(TRIM(MID(edits!C4, FIND("->",edits!C4) + 2, LEN(edits!C4))),"") | H4: =IF(ISNUMBER(SEARCH("removed", edits!D4)), "", IF(ISNUMBER(SEARCH("->", edits!D4)), TRIM(LEFT(edits!D4, FIND("->", edits!D4)-1)), IF(ISNUMBER(SEARCH("->", edits!C4)), TRIM(LEFT(edits!C4, FIND("->", edits!C4)-1)), edits!D4))) -> stagnant water | I4: =IF(ISNUMBER(SEARCH("->", edits!D4)), TRIM(MID(edits!D4, FIND("->", edits!D4) + 2, LEN(edits!D4))), IF(ISNUMBER(SEARCH("->", edits!C4)), TRIM(MID(edits!C4, FIND("->", edits!C4) + 2, LEN(edits!C4))), "")) | J4: {=IF(OR(H4="", I4=""), "", INDEX(all_edges!D:D, MATCH(1, (all_edges!A:A=B4) * (all_edges!B:B=H4) * (all_edges!C:C=I4), 0) ) )} | K4: =edits!E4 -> clarification
A5: 4 | B5: =edits!B5 -> 2 | C5: =IF(ISNUMBER(SEARCH("->",edits!C5)), "Edge", "Node") -> Node | D5: =edits!D5 -> sedentarisation | F5: =IFERROR(TRIM(LEFT(edits!C5, FIND("->", edits!C5) - 1)),edits!C5) -> permanance of homestead/sedentarisation | G5: =IFERROR(TRIM(MID(edits!C5, FIND("->",edits!C5) + 2, LEN(edits!C5))),"") | H5: =IF(ISNUMBER(SEARCH("removed", edits!D5)), "", IF(ISNUMBER(SEARCH("->", edits!D5)), TRIM(LEFT(edits!D5, FIND("->", edits!D5)-1)), IF(ISNUMBER(SEARCH("->", edits!C5)), TRIM(LEFT(edits!C5, FIND("->", edits!C5)-1)), edits!D5))) -> sedentarisation | I5: =IF(ISNUMBER(SEARCH("->", edits!D5)), TRIM(MID(edits!D5, FIND("->", edits!D5) + 2, LEN(edits!D5))), IF(ISNUMBER(SEARCH("->", edits!C5)), TRIM(MID(edits!C5, FIND("->", edits!C5) + 2, LEN(edits!C5))), "")) | J5: {=IF(OR(H5="", I5=""), "", INDEX(all_edges!D:D, MATCH(1, (all_edges!A:A=B5) * (all_edges!B:B=H5) * (all_edges!C:C=I5), 0) ) )} | K5: =edits!E5 -> simplification
A6: 5 | B6: =edits!B6 -> 2 | C6: =IF(ISNUMBER(SEARCH("->",edits!C6)), "Edge", "Node") -> Node | D6: =edits!D6 -> household possessions | F6: =IFERROR(TRIM(LEFT(edits!C6, FIND("->", edits!C6) - 1)),edits!C6) -> more possessions | G6: =IFERROR(TRIM(MID(edits!C6, FIND("->",edits!C6) + 2, LEN(edits!C6))),"") | H6: =IF(ISNUMBER(SEARCH("removed", edits!D6)), "", IF(ISNUMBER(SEARCH("->", edits!D6)), TRIM(LEFT(edits!D6, FIND("->", edits!D6)-1)), IF(ISNUMBER(SEARCH("->", edits!C6)), TRIM(LEFT(edits!C6, FIND("->", edits!C6)-1)), edits!D6))) -> household possessions | I6: =IF(ISNUMBER(SEARCH("->", edits!D6)), TRIM(MID(edits!D6, FIND("->", edits!D6) + 2, LEN(edits!D6))), IF(ISNUMBER(SEARCH("->", edits!C6)), TRIM(MID(edits!C6, FIND("->", edits!C6) + 2, LEN(edits!C6))), "")) | J6: {=IF(OR(H6="", I6=""), "", INDEX(all_edges!D:D, MATCH(1, (all_edges!A:A=B6) * (all_edges!B:B=H6) * (all_edges!C:C=I6), 0) ) )} | K6: =edits!E6 -> removed comparative degree marker as concepts must be variable and added 'household' for clarification
A7: 6 | B7: =edits!B7 -> 2 | C7: =IF(ISNUMBER(SEARCH("->",edits!C7)), "Edge", "Node") -> Node | D7: =edits!D7 -> livestock body condition | F7: =IFERROR(TRIM(LEFT(edits!C7, FIND("->", edits!C7) - 1)),edits!C7) -> livestock condition | G7: =IFERROR(TRIM(MID(edits!C7, FIND("->",edits!C7) + 2, LEN(edits!C7))),"") | H7: =IF(ISNUMBER(SEARCH("removed", edits!D7)), "", IF(ISNUMBER(SEARCH("->", edits!D7)), TRIM(LEFT(edits!D7, FIND("->", edits!D7)-1)), IF(ISNUMBER(SEARCH("->", edits!C7)), TRIM(LEFT(edits!C7, FIND("->", edits!C7)-1)), edits!D7))) -> livestock body condition | I7: =IF(ISNUMBER(SEARCH("->", edits!D7)), TRIM(MID(edits!D7, FIND("->", edits!D7) + 2, LEN(edits!D7))), IF(ISNUMBER(SEARCH("->", edits!C7)), TRIM(MID(edits!C7, FIND("->", edits!C7) + 2, LEN(edits!C7))), "")) | J7: {=IF(OR(H7="", I7=""), "", INDEX(all_edges!D:D, MATCH(1, (all_edges!A:A=B7) * (all_edges!B:B=H7) * (all_edges!C:C=I7), 0) ) )} | K7: =edits!E7 -> clarification
A8: 7 | B8: =edits!B8 -> 2 | C8: =IF(ISNUMBER(SEARCH("->",edits!C8)), "Edge", "Node") -> Node | D8: =edits!D8 -> removed | F8: =IFERROR(TRIM(LEFT(edits!C8, FIND("->", edits!C8) - 1)),edits!C8) -> livestock colour | G8: =IFERROR(TRIM(MID(edits!C8, FIND("->",edits!C8) + 2, LEN(edits!C8))),"") | H8: =IF(ISNUMBER(SEARCH("removed", edits!D8)), "", IF(ISNUMBER(SEARCH("->", edits!D8)), TRIM(LEFT(edits!D8, FIND("->", edits!D8)-1)), IF(ISNUMBER(SEARCH("->", edits!C8)), TRIM(LEFT(edits!C8, FIND("->", edits!C8)-1)), edits!D8))) | I8: =IF(ISNUMBER(SEARCH("->", edits!D8)), TRIM(MID(edits!D8, FIND("->", edits!D8) + 2, LEN(edits!D8))), IF(ISNUMBER(SEARCH("->", edits!C8)), TRIM(MID(edits!C8, FIND("->", edits!C8) + 2, LEN(edits!C8))), "")) | J8: {=IF(OR(H8="", I8=""), "", INDEX(all_edges!D:D, MATCH(1, (all_edges!A:A=B8) * (all_edges!B:B=H8) * (all_edges!C:C=I8), 0) ) )} | K8: =edits!E8 -> equivalent to livestock body condition
A9: 8 | B9: =edits!B9 -> 2 | C9: =IF(ISNUMBER(SEARCH("->",edits!C9)), "Edge", "Node") -> Node | D9: =edits!D9 -> environmental faecal contamination | F9: =IFERROR(TRIM(LEFT(edits!C9, FIND("->", edits!C9) - 1)),edits!C9) -> accumulation of dirtiness (rubbish & faeces) | G9: =IFERROR(TRIM(MID(edits!C9, FIND("->",edits!C9) + 2, LEN(edits!C9))),"") | H9: =IF(ISNUMBER(SEARCH("removed", edits!D9)), "", IF(ISNUMBER(SEARCH("->", edits!D9)), TRIM(LEFT(edits!D9, FIND("->", edits!D9)-1)), IF(ISNUMBER(SEARCH("->", edits!C9)), TRIM(LEFT(edits!C9, FIND("->", edits!C9)-1)), edits!D9))) -> environmental faecal contamination | I9: =IF(ISNUMBER(SEARCH("->", edits!D9)), TRIM(MID(edits!D9, FIND("->", edits!D9) + 2, LEN(edits!D9))), IF(ISNUMBER(SEARCH("->", edits!C9)), TRIM(MID(edits!C9, FIND("->", edits!C9) + 2, LEN(edits!C9))), "")) | J9: {=IF(OR(H9="", I9=""), "", INDEX(all_edges!D:D, MATCH(1, (all_edges!A:A=B9) * (all_edges!B:B=H9) * (all_edges!C:C=I9), 0) ) )} | K9: =edits!E9 -> harmonisation with other FCMS
A10: 9 | B10: =edits!B10 -> 2 | C10: =IF(ISNUMBER(SEARCH("->",edits!C10)), "Edge", "Node") -> Node | D10: =edits!D10 -> income | F10: =IFERROR(TRIM(LEFT(edits!C10, FIND("->", edits!C10) - 1)),edits!C10) -> livelihood | G10: =IFERROR(TRIM(MID(edits!C10, FIND("->",edits!C10) + 2, LEN(edits!C10))),"") | H10: =IF(ISNUMBER(SEARCH("removed", edits!D10)), "", IF(ISNUMBER(SEARCH("->", edits!D10)), TRIM(LEFT(edits!D10, FIND("->", edits!D10)-1)), IF(ISNUMBER(SEARCH("->", edits!C10)), TRIM(LEFT(edits!C10, FIND("->", edits!C10)-1)), edits!D10))) -> income | I10: =IF(ISNUMBER(SEARCH("->", edits!D10)), TRIM(MID(edits!D10, FIND("->", edits!D10) + 2, LEN(edits!D10))), IF(ISNUMBER(SEARCH("->", edits!C10)), TRIM(MID(edits!C10, FIND("->", edits!C10) + 2, LEN(edits!C10))), "")) | J10: {=IF(OR(H10="", I10=""), "", INDEX(all_edges!D:D, MATCH(1, (all_edges!A:A=B10) * (all_edges!B:B=H10) * (all_edges!C:C=I10), 0) ) )} | K10: =edits!E10 -> livelihood cannot increase or decrease
A11: 10 | B11: =edits!B11 -> 2 | C11: =IF(ISNUMBER(SEARCH("->",edits!C11)), "Edge", "Node") -> Edge | D11: =edits!D11 -> added weight -2 | F11: =IFERROR(TRIM(LEFT(edits!C11, FIND("->", edits!C11) - 1)),edits!C11) -> livestock disease | G11: =IFERROR(TRIM(MID(edits!C11, FIND("->",edits!C11) + 2, LEN(edits!C11))),"") -> livestock body condition | H11: =IF(ISNUMBER(SEARCH("removed", edits!D11)), "", IF(ISNUMBER(SEARCH("->", edits!D11)), TRIM(LEFT(edits!D11, FIND("->", edits!D11)-1)), IF(ISNUMBER(SEARCH("->", edits!C11)), TRIM(LEFT(edits!C11, FIND("->", edits!C11)-1)), edits!D11))) -> livestock disease | I11: =IF(ISNUMBER(SEARCH("->", edits!D11)), TRIM(MID(edits!D11, FIND("->", edits!D11) + 2, LEN(edits!D11))), IF(ISNUMBER(SEARCH("->", edits!C11)), TRIM(MID(edits!C11, FIND("->", edits!C11) + 2, LEN(edits!C11))), "")) -> livestock body condition | J11: {=IF(OR(H11="", I11=""), "", INDEX(all_edges!D:D, MATCH(1, (all_edges!A:A=B11) * (all_edges!B:B=H11) * (all_edges!C:C=I11), 0) ) )} -> -2 | K11: =edits!E11 -> sign recorded but no weight, assumed central value
A12: 11 | B12: =edits!B12 -> 2 | C12: =IF(ISNUMBER(SEARCH("->",edits!C12)), "Edge", "Node") -> Node | D12: =edits!D12 -> removed | F12: =IFERROR(TRIM(LEFT(edits!C12, FIND("->", edits!C12) - 1)),edits!C12) -> accumulation of livestock faeces | G12: =IFERROR(TRIM(MID(edits!C12, FIND("->",edits!C12) + 2, LEN(edits!C12))),"") | H12: =IF(ISNUMBER(SEARCH("removed", edits!D12)), "", IF(ISNUMBER(SEARCH("->", edits!D12)), TRIM(LEFT(edits!D12, FIND("->", edits!D12)-1)), IF(ISNUMBER(SEARCH("->", edits!C12)), TRIM(LEFT(edits!C12, FIND("->", edits!C12)-1)), edits!D12))) | I12: =IF(ISNUMBER(SEARCH("->", edits!D12)), TRIM(MID(edits!D12, FIND("->", edits!D12) + 2, LEN(edits!D12))), IF(ISNUMBER(SEARCH("->", edits!C12)), TRIM(MID(edits!C12, FIND("->", edits!C12) + 2, LEN(edits!C12))), "")) | J12: {=IF(OR(H12="", I12=""), "", INDEX(all_edges!D:D, MATCH(1, (all_edges!A:A=B12) * (all_edges!B:B=H12) * (all_edges!C:C=I12), 0) ) )} | K12: =edits!E12 -> equivalent to 'environmental faecal contamination'
A13: 12 | B13: =edits!B13 -> 2 | C13: =IF(ISNUMBER(SEARCH("->",edits!C13)), "Edge", "Node") -> Node | D13: =edits!D13 -> mobility | F13: =IFERROR(TRIM(LEFT(edits!C13, FIND("->", edits!C13) - 1)),edits!C13) -> mobility of homestead | G13: =IFERROR(TRIM(MID(edits!C13, FIND("->",edits!C13) + 2, LEN(edits!C13))),"") | H13: =IF(ISNUMBER(SEARCH("removed", edits!D13)), "", IF(ISNUMBER(SEARCH("->", edits!D13)), TRIM(LEFT(edits!D13, FIND("->", edits!D13)-1)), IF(ISNUMBER(SEARCH("->", edits!C13)), TRIM(LEFT(edits!C13, FIND("->", edits!C13)-1)), edits!D13))) -> mobility | I13: =IF(ISNUMBER(SEARCH("->", edits!D13)), TRIM(MID(edits!D13, FIND("->", edits!D13) + 2, LEN(edits!D13))), IF(ISNUMBER(SEARCH("->", edits!C13)), TRIM(MID(edits!C13, FIND("->", edits!C13) + 2, LEN(edits!C13))), "")) | J13: {=IF(OR(H13="", I13=""), "", INDEX(all_edges!D:D, MATCH(1, (all_edges!A:A=B13) * (all_edges!B:B=H13) * (all_edges!C:C=I13), 0) ) )} | K13: =edits!E13 -> harmonisation with other FCMS
... A1126: 1125 | B1126: =edits!B1126 -> 36 | C1126: =IF(ISNUMBER(SEARCH("->",edits!C1126)), "Edge", "Node") -> Node | D1126: =edits!D1126 -> veterinary services | F1126: =IFERROR(TRIM(LEFT(edits!C1126, FIND("->", edits!C1126) - 1)),edits!C1126) -> livestock drug purchase | G1126: =IFERROR(TRIM(MID(edits!C1126, FIND("->",edits!C1126) + 2, LEN(edits!C1126))),"") | H1126: =IF(ISNUMBER(SEARCH("removed", edits!D1126)), "", IF(ISNUMBER(SEARCH("->", edits!D1126)), TRIM(LEFT(edits!D1126, FIND("->", edits!D1126)-1)), IF(ISNUMBER(SEARCH("->", edits!C1126)), TRIM(LEFT(edits!C1126, FIND("->", edits!C1126)-1)), edits!D1126))) -> veterinary services | I1126: =IF(ISNUMBER(SEARCH("->", edits!D1126)), TRIM(MID(edits!D1126, FIND("->", edits!D1126) + 2, LEN(edits!D1126))), IF(ISNUMBER(SEARCH("->", edits!C1126)), TRIM(MID(edits!C1126, FIND("->", edits!C1126) + 2, LEN(edits!C1126))), "")) | J1126: {=IF(OR(H1126="", I1126=""), "", INDEX(all_edges!D:D, MATCH(1, (all_edges!A:A=B1126) * (all_edges!B:B=H1126) * (all_edges!C:C=I1126), 0) ) )} | K1126: =edits!E1126 -> harmonisation with other FCMs
I1164: =IF(ISNUMBER(SEARCH("->", edits!D1191)), TRIM(MID(edits!D1191, FIND("->", edits!D1191) + 2, LEN(edits!D1191))), IF(ISNUMBER(SEARCH("->", edits!C1191)), TRIM(MID(edits!C1191, FIND("->", edits!C1191) + 2, LEN(edits!C1191))), "")) | J1164: {=IF(OR(H1164="", I1164=""), "", INDEX(all_edges!D:D, MATCH(1, (all_edges!A:A=B1164) * (all_edges!B:B=H1164) * (all_edges!C:C=I1164), 0) ) )}
I1165: =IF(ISNUMBER(SEARCH("->", edits!D1192)), TRIM(MID(edits!D1192, FIND("->", edits!D1192) + 2, LEN(edits!D1192))), IF(ISNUMBER(SEARCH("->", edits!C1192)), TRIM(MID(edits!C1192, FIND("->", edits!C1192) + 2, LEN(edits!C1192))), "")) | J1165: {=IF(OR(H1165="", I1165=""), "", INDEX(all_edges!D:D, MATCH(1, (all_edges!A:A=B1165) * (all_edges!B:B=H1165) * (all_edges!C:C=I1165), 0) ) )}
I1166: =IF(ISNUMBER(SEARCH("->", edits!D1193)), TRIM(MID(edits!D1193, FIND("->", edits!D1193) + 2, LEN(edits!D1193))), IF(ISNUMBER(SEARCH("->", edits!C1193)), TRIM(MID(edits!C1193, FIND("->", edits!C1193) + 2, LEN(edits!C1193))), "")) | J1166: {=IF(OR(H1166="", I1166=""), "", INDEX(all_edges!D:D, MATCH(1, (all_edges!A:A=B1166) * (all_edges!B:B=H1166) * (all_edges!C:C=I1166), 0) ) )}
I1167: =IF(ISNUMBER(SEARCH("->", edits!D1194)), TRIM(MID(edits!D1194, FIND("->", edits!D1194) + 2, LEN(edits!D1194))), IF(ISNUMBER(SEARCH("->", edits!C1194)), TRIM(MID(edits!C1194, FIND("->", edits!C1194) + 2, LEN(edits!C1194))), "")) | J1167: {=IF(OR(H1167="", I1167=""), "", INDEX(all_edges!D:D, MATCH(1, (all_edges!A:A=B1167) * (all_edges!B:B=H1167) * (all_edges!C:C=I1167), 0) ) )}
I1168: =IF(ISNUMBER(SEARCH("->", edits!D1195)), TRIM(MID(edits!D1195, FIND("->", edits!D1195) + 2, LEN(edits!D1195))), IF(ISNUMBER(SEARCH("->", edits!C1195)), TRIM(MID(edits!C1195, FIND("->", edits!C1195) + 2, LEN(edits!C1195))), "")) | J1168: {=IF(OR(H1168="", I1168=""), "", INDEX(all_edges!D:D, MATCH(1, (all_edges!A:A=B1168) * (all_edges!B:B=H1168) * (all_edges!C:C=I1168), 0) ) )}
I1169: =IF(ISNUMBER(SEARCH("->", edits!D1196)), TRIM(MID(edits!D1196, FIND("->", edits!D1196) + 2, LEN(edits!D1196))), IF(ISNUMBER(SEARCH("->", edits!C1196)), TRIM(MID(edits!C1196, FIND("->", edits!C1196) + 2, LEN(edits!C1196))), "")) | J1169: {=IF(OR(H1169="", I1169=""), "", INDEX(all_edges!D:D, MATCH(1, (all_edges!A:A=B1169) * (all_edges!B:B=H1169) * (all_edges!C:C=I1169), 0) ) )}
I1170: =IF(ISNUMBER(SEARCH("->", edits!D1197)), TRIM(MID(edits!D1197, FIND("->", edits!D1197) + 2, LEN(edits!D1197))), IF(ISNUMBER(SEARCH("->", edits!C1197)), TRIM(MID(edits!C1197, FIND("->", edits!C1197) + 2, LEN(edits!C1197))), "")) | J1170: {=IF(OR(H1170="", I1170=""), "", INDEX(all_edges!D:D, MATCH(1, (all_edges!A:A=B1170) * (all_edges!B:B=H1170) * (all_edges!C:C=I1170), 0) ) )}
I1171: =IF(ISNUMBER(SEARCH("->", edits!D1198)), TRIM(MID(edits!D1198, FIND("->", edits!D1198) + 2, LEN(edits!D1198))), IF(ISNUMBER(SEARCH("->", edits!C1198)), TRIM(MID(edits!C1198, FIND("->", edits!C1198) + 2, LEN(edits!C1198))), "")) | J1171: {=IF(OR(H1171="", I1171=""), "", INDEX(all_edges!D:D, MATCH(1, (all_edges!A:A=B1171) * (all_edges!B:B=H1171) * (all_edges!C:C=I1171), 0) ) )}
I1172: =IF(ISNUMBER(SEARCH("->", edits!D1199)), TRIM(MID(edits!D1199, FIND("->", edits!D1199) + 2, LEN(edits!D1199))), IF(ISNUMBER(SEARCH("->", edits!C1199)), TRIM(MID(edits!C1199, FIND("->", edits!C1199) + 2, LEN(edits!C1199))), "")) | J1172: {=IF(OR(H1172="", I1172=""), "", INDEX(all_edges!D:D, MATCH(1, (all_edges!A:A=B1172) * (all_edges!B:B=H1172) * (all_edges!C:C=I1172), 0) ) )}
I1173: =IF(ISNUMBER(SEARCH("->", edits!D1200)), TRIM(MID(edits!D1200, FIND("->", edits!D1200) + 2, LEN(edits!D1200))), IF(ISNUMBER(SEARCH("->", edits!C1200)), TRIM(MID(edits!C1200, FIND("->", edits!C1200) + 2, LEN(edits!C1200))), "")) | J1173: {=IF(OR(H1173="", I1173=""), "", INDEX(all_edges!D:D, MATCH(1, (all_edges!A:A=B1173) * (all_edges!B:B=H1173) * (all_edges!C:C=I1173), 0) ) )}
I1174: =IF(ISNUMBER(SEARCH("->", edits!D1201)), TRIM(MID(edits!D1201, FIND("->", edits!D1201) + 2, LEN(edits!D1201))), IF(ISNUMBER(SEARCH("->", edits!C1201)), TRIM(MID(edits!C1201, FIND("->", edits!C1201) + 2, LEN(edits!C1201))), "")) | J1174: {=IF(OR(H1174="", I1174=""), "", INDEX(all_edges!D:D, MATCH(1, (all_edges!A:A=B1174) * (all_edges!B:B=H1174) * (all_edges!C:C=I1174), 0) ) )}
I1175: =IF(ISNUMBER(SEARCH("->", edits!D1202)), TRIM(MID(edits!D1202, FIND("->", edits!D1202) + 2, LEN(edits!D1202))), IF(ISNUMBER(SEARCH("->", edits!C1202)), TRIM(MID(edits!C1202, FIND("->", edits!C1202) + 2, LEN(edits!C1202))), "")) | J1175: {=IF(OR(H1175="", I1175=""), "", INDEX(all_edges!D:D, MATCH(1, (all_edges!A:A=B1175) * (all_edges!B:B=H1175) * (all_edges!C:C=I1175), 0) ) )}
... I1222: =IF(ISNUMBER(SEARCH("->", edits!D1249)), TRIM(MID(edits!D1249, FIND("->", edits!D1249) + 2, LEN(edits!D1249))), IF(ISNUMBER(SEARCH("->", edits!C1249)), TRIM(MID(edits!C1249, FIND("->", edits!C1249) + 2, LEN(edits!C1249))), "")) | J1222: {=IF(OR(H1222="", I1222=""), "", INDEX(all_edges!D:D, MATCH(1, (all_edges!A:A=B1222) * (all_edges!B:B=H1222) * (all_edges!C:C=I1222), 0) ) )}
I1223: =IF(ISNUMBER(SEARCH("->", edits!D1250)), TRIM(MID(edits!D1250, FIND("->", edits!D1250) + 2, LEN(edits!D1250))), IF(ISNUMBER(SEARCH("->", edits!C1250)), TRIM(MID(edits!C1250, FIND("->", edits!C1250) + 2, LEN(edits!C1250))), ""))
I1224: =IF(ISNUMBER(SEARCH("->", edits!D1251)), TRIM(MID(edits!D1251, FIND("->", edits!D1251) + 2, LEN(edits!D1251))), IF(ISNUMBER(SEARCH("->", edits!C1251)), TRIM(MID(edits!C1251, FIND("->", edits!C1251) + 2, LEN(edits!C1251))), ""))
I1225: =IF(ISNUMBER(SEARCH("->", edits!D1252)), TRIM(MID(edits!D1252, FIND("->", edits!D1252) + 2, LEN(edits!D1252))), IF(ISNUMBER(SEARCH("->", edits!C1252)), TRIM(MID(edits!C1252, FIND("->", edits!C1252) + 2, LEN(edits!C1252))), ""))
I1226: =IF(ISNUMBER(SEARCH("->", edits!D1253)), TRIM(MID(edits!D1253, FIND("->", edits!D1253) + 2, LEN(edits!D1253))), IF(ISNUMBER(SEARCH("->", edits!C1253)), TRIM(MID(edits!C1253, FIND("->", edits!C1253) + 2, LEN(edits!C1253))), ""))
I1227: =IF(ISNUMBER(SEARCH("->", edits!D1254)), TRIM(MID(edits!D1254, FIND("->", edits!D1254) + 2, LEN(edits!D1254))), IF(ISNUMBER(SEARCH("->", edits!C1254)), TRIM(MID(edits!C1254, FIND("->", edits!C1254) + 2, LEN(edits!C1254))), ""))
I1228: =IF(ISNUMBER(SEARCH("->", edits!D1255)), TRIM(MID(edits!D1255, FIND("->", edits!D1255) + 2, LEN(edits!D1255))), IF(ISNUMBER(SEARCH("->", edits!C1255)), TRIM(MID(edits!C1255, FIND("->", edits!C1255) + 2, LEN(edits!C1255))), ""))
I1229: =IF(ISNUMBER(SEARCH("->", edits!D1256)), TRIM(MID(edits!D1256, FIND("->", edits!D1256) + 2, LEN(edits!D1256))), IF(ISNUMBER(SEARCH("->", edits!C1256)), TRIM(MID(edits!C1256, FIND("->", edits!C1256) + 2, LEN(edits!C1256))), ""))
I1230: =IF(ISNUMBER(SEARCH("->", edits!D1257)), TRIM(MID(edits!D1257, FIND("->", edits!D1257) + 2, LEN(edits!D1257))), IF(ISNUMBER(SEARCH("->", edits!C1257)), TRIM(MID(edits!C1257, FIND("->", edits!C1257) + 2, LEN(edits!C1257))), ""))
I1231: =IF(ISNUMBER(SEARCH("->", edits!D1258)), TRIM(MID(edits!D1258, FIND("->", edits!D1258) + 2, LEN(edits!D1258))), IF(ISNUMBER(SEARCH("->", edits!C1258)), TRIM(MID(edits!C1258, FIND("->", edits!C1258) + 2, LEN(edits!C1258))), ""))
I1232: =IF(ISNUMBER(SEARCH("->", edits!D1259)), TRIM(MID(edits!D1259, FIND("->", edits!D1259) + 2, LEN(edits!D1259))), IF(ISNUMBER(SEARCH("->", edits!C1259)), TRIM(MID(edits!C1259, FIND("->", edits!C1259) + 2, LEN(edits!C1259))), ""))
I1233: =IF(ISNUMBER(SEARCH("->", edits!D1260)), TRIM(MID(edits!D1260, FIND("->", edits!D1260) + 2, LEN(edits!D1260))), IF(ISNUMBER(SEARCH("->", edits!C1260)), TRIM(MID(edits!C1260, FIND("->", edits!C1260) + 2, LEN(edits!C1260))), ""))
I1234: =IF(ISNUMBER(SEARCH("->", edits!D1261)), TRIM(MID(edits!D1261, FIND("->", edits!D1261) + 2, LEN(edits!D1261))), IF(ISNUMBER(SEARCH("->", edits!C1261)), TRIM(MID(edits!C1261, FIND("->", edits!C1261) + 2, LEN(edits!C1261))), ""))
... I1268: =IF(ISNUMBER(SEARCH("->", edits!D1295)), TRIM(MID(edits!D1295, FIND("->", edits!D1295) + 2, LEN(edits!D1295))), IF(ISNUMBER(SEARCH("->", edits!C1295)), TRIM(MID(edits!C1295, FIND("->", edits!C1295) + 2, LEN(edits!C1295))), ""))

Sheet Sheet1
A1: rename
A2: remove
A3: add
A4: merge
A5: split
A6: weight change
A7: weight sign change
